<?xml version="1.0"?>
<opencv_storage>
<stage10>
  <maxWeakCount>6</maxWeakCount>
  <stageThreshold>-1.6419985294342041e+00</stageThreshold>
  <weakClassifiers>
    <_>
      <internalNodes>
        0 -1 5948 5.9580951929092407e-02</internalNodes>
      <leafValues>
        -8.5425102710723877e-01 -7.0063695311546326e-02</leafValues></_>
    <_>
      <internalNodes>
        0 -1 142575 1.9292029901407659e-04</internalNodes>
      <leafValues>
        -7.3664909601211548e-01 1.4722277224063873e-01</leafValues></_>
    <_>
      <internalNodes>
        0 -1 102720 -4.0185003308579326e-04</internalNodes>
      <leafValues>
        3.8348740339279175e-01 -5.3335756063461304e-01</leafValues></_>
    <_>
      <internalNodes>
        0 -1 143025 5.7643576292321086e-04</internalNodes>
      <leafValues>
        -4.1092300415039063e-01 4.7541227936744690e-01</leafValues></_>
    <_>
      <internalNodes>
        0 -1 48462 -7.6217666268348694e-02</internalNodes>
      <leafValues>
        4.4747281074523926e-01 -4.4473245739936829e-01</leafValues></_>
    <_>
      <internalNodes>
        0 -1 138275 3.7524866638705134e-04</internalNodes>
      <leafValues>
        -3.3014455437660217e-01 5.5000084638595581e-01</leafValues></_></weakClassifiers></stage10>
</opencv_storage>
