<?xml version="1.0"?>
<opencv_storage>
<stage8>
  <maxWeakCount>5</maxWeakCount>
  <stageThreshold>-1.5984882116317749e+00</stageThreshold>
  <weakClassifiers>
    <_>
      <internalNodes>
        0 -1 401763 3.5805101506412029e-03</internalNodes>
      <leafValues>
        -8.6626744270324707e-01 9.0909093618392944e-02</leafValues></_>
    <_>
      <internalNodes>
        0 -1 726278 -3.3395808190107346e-02</internalNodes>
      <leafValues>
        4.6439889073371887e-01 -6.1703538894653320e-01</leafValues></_>
    <_>
      <internalNodes>
        0 -1 669866 1.2277236673980951e-03</internalNodes>
      <leafValues>
        -5.6909579038619995e-01 4.6455380320549011e-01</leafValues></_>
    <_>
      <internalNodes>
        0 -1 468236 -4.0630606235936284e-04</internalNodes>
      <leafValues>
        3.1221529841423035e-01 -7.6171529293060303e-01</leafValues></_>
    <_>
      <internalNodes>
        0 -1 189975 -3.8253419101238251e-02</internalNodes>
      <leafValues>
        -9.1575592756271362e-01 2.5844919681549072e-01</leafValues></_></weakClassifiers></stage8>
</opencv_storage>
