<?xml version="1.0"?>
<opencv_storage>
<stage0>
  <maxWeakCount>3</maxWeakCount>
  <stageThreshold>-1.0966325998306274e+00</stageThreshold>
  <weakClassifiers>
    <_>
      <internalNodes>
        0 -1 724598 -3.9749737828969955e-02</internalNodes>
      <leafValues>
        6.8807339668273926e-01 -8.9768338203430176e-01</leafValues></_>
    <_>
      <internalNodes>
        0 -1 382570 1.2821868062019348e-02</internalNodes>
      <leafValues>
        -8.5245048999786377e-01 4.4464725255966187e-01</leafValues></_>
    <_>
      <internalNodes>
        0 -1 732717 -6.3414508476853371e-03</internalNodes>
      <leafValues>
        6.5350127220153809e-01 -6.3395249843597412e-01</leafValues></_></weakClassifiers></stage0>
</opencv_storage>
